{
  "pixels_per_meter": 12,
  "readers": [
    {
      "x": 295,
      "y": 1206
    },
    {
      "x": 931,
      "y": 1217
    },
    {
      "x": 1440,
      "y": 1219
    },
    {
      "x": 1886,
      "y": 1257
    },
    {
      "x": 319,
      "y": 646
    },
    {
      "x": 930,
      "y": 653
    },
    {
      "x": 1450,
      "y": 654
    },
    {
      "x": 1794,
      "y": 666
    },
    {
      "x": 239,
      "y": 219
    },
    {
      "x": 1046,
      "y": 242
    },
    {
      "x": 1571,
      "y": 234
    },
    {
      "x": 1890,
      "y": 247
    }
  ]
}

